breast/__init__.py
breast/py.typed
breast-0.1.0.dist-info/METADATA
breast-0.1.0.dist-info/WHEEL
breast-0.1.0.dist-info/RECORD
