Metadata-Version: 2.4
Name: breast
Version: 0.1.0
Summary: breast
Author-email: Tom Ouellette <t.ouellette@mail.utoronto.ca>
Requires-Python: >=3.12
